{
	"CONTROLS" : 
	[
		{
			"DEFAULT" : 0,
			"DESCRIPTION" : "",
			"MAX" : 1,
			"MIN" : 0,
			"NAME" : "MouseXY",
			"TYPE" : "xy",
			"UI_GROUP" : "defaults"
		},
		{
			"DEFAULT" : 0,
			"DESCRIPTION" : "",
			"MAX" : 1,
			"MIN" : 0,
			"NAME" : "MouseClick",
			"TYPE" : "toggle",
			"UI_GROUP" : "defaults"
		}
	],
	"CREDIT" : "milesWaugh",
	"DESCRIPTION" : "I finally learned how to use buffers, yay! This works by repeatedly averaging what would be the next frame with the previous frame, to make the next frame.",
	"HEIGHT" : 720,
	"IMAGE_PATH" : "single-buffer_motion_blur.png",
	"PASSES" : 
	[
		{
			"FLOAT" : true,
			"HEIGHT" : 720,
			"TARGET" : "BuffA",
			"WIDTH" : 1280
		}
	],
	"TITLE" : "Single-Buffer Motion Blur",
	"WIDTH" : 1280
}